{
  "nixpkgs-flox": {
    "x86_64-darwin": {
      "stable": {
        "nginx": {
          "latest": {
            "cache": {
              "doc": {
                "https://cache.nixos.org": {}
              },
              "out": {
                "https://cache.nixos.org": {}
              }
            },
            "element": {
              "attrPath": [
                "legacyPackages",
                "x86_64-darwin",
                "nginx"
              ],
              "originalUrl": "flake:nixpkgs",
              "storePaths": [
                "/nix/store/pnngg1cvn6jxyvryqrg50yxx5slxpnbv-nginx-1.22.1"
              ],
              "url": "github:flox/nixpkgs/d0d55259081f0b97c828f38559cad899d351cad1"
            },
            "eval": {
              "meta": {
                "description": "A reverse proxy and lightweight webserver",
                "outputsToInstall": [
                  "out"
                ],
                "position": "/nix/store/32cp7y0cf36h3xp0fqwy2nf432fpcaci-source/pkgs/servers/http/nginx/generic.nix:188",
                "unfree": false
              },
              "name": "nginx-1.22.1",
              "outputs": {
                "doc": "/nix/store/0w5hachvs2zyl2f1ybwlvg2764fgwy3k-nginx-1.22.1-doc",
                "out": "/nix/store/pnngg1cvn6jxyvryqrg50yxx5slxpnbv-nginx-1.22.1"
              },
              "pname": "nginx",
              "system": "x86_64-darwin",
              "version": "1.22.1"
            },
            "publish_element": {
              "attrPath": [
                "evalCatalog",
                "x86_64-darwin",
                "stable",
                "nginx"
              ],
              "originalUrl": "flake:nixpkgs-flox",
              "storePaths": [
                "/nix/store/pnngg1cvn6jxyvryqrg50yxx5slxpnbv-nginx-1.22.1"
              ],
              "url": "flake:nixpkgs-flox/34ee8469ab62af53cd25a839de33950b19126dc8"
            },
            "schema": 1,
            "source": {
              "locked": {
                "lastModified": 1676973346,
                "revCount": 456418
              }
            },
            "type": "catalogRender"
          }
        },
        "nodejs": {
          "latest": {
            "cache": {
              "libv8": {
                "https://cache.nixos.org": {}
              },
              "out": {
                "https://cache.nixos.org": {}
              }
            },
            "element": {
              "attrPath": [
                "legacyPackages",
                "x86_64-darwin",
                "nodejs"
              ],
              "originalUrl": "flake:nixpkgs",
              "storePaths": [
                "/nix/store/1nvnqs64rc17w9r624qfcabk3cj87zw5-nodejs-18.14.1"
              ],
              "url": "github:flox/nixpkgs/d0d55259081f0b97c828f38559cad899d351cad1"
            },
            "eval": {
              "meta": {
                "description": "Event-driven I/O framework for the V8 JavaScript engine",
                "outputsToInstall": [
                  "out"
                ],
                "position": "/nix/store/32cp7y0cf36h3xp0fqwy2nf432fpcaci-source/pkgs/development/web/nodejs/v18.nix:12",
                "unfree": false
              },
              "name": "nodejs-18.14.1",
              "outputs": {
                "libv8": "/nix/store/rsp63jprwsaix82f5v1fw3h0wn1xs3zi-nodejs-18.14.1-libv8",
                "out": "/nix/store/1nvnqs64rc17w9r624qfcabk3cj87zw5-nodejs-18.14.1"
              },
              "pname": "nodejs",
              "system": "x86_64-darwin",
              "version": "18.14.1"
            },
            "publish_element": {
              "attrPath": [
                "evalCatalog",
                "x86_64-darwin",
                "stable",
                "nodejs"
              ],
              "originalUrl": "flake:nixpkgs-flox",
              "storePaths": [
                "/nix/store/1nvnqs64rc17w9r624qfcabk3cj87zw5-nodejs-18.14.1"
              ],
              "url": "flake:nixpkgs-flox/34ee8469ab62af53cd25a839de33950b19126dc8"
            },
            "schema": 1,
            "source": {
              "locked": {
                "lastModified": 1676973346,
                "revCount": 456418
              }
            },
            "type": "catalogRender"
          }
        },
        "redis": {
          "latest": {
            "cache": {
              "out": {
                "https://cache.nixos.org": {}
              }
            },
            "element": {
              "attrPath": [
                "legacyPackages",
                "x86_64-darwin",
                "redis"
              ],
              "originalUrl": "flake:nixpkgs",
              "storePaths": [
                "/nix/store/had7hr6vi53k6ba0p8mkhiwr2652r0rg-redis-7.0.8"
              ],
              "url": "github:flox/nixpkgs/d0d55259081f0b97c828f38559cad899d351cad1"
            },
            "eval": {
              "meta": {
                "description": "An open source, advanced key-value store",
                "outputsToInstall": [
                  "out"
                ],
                "position": "/nix/store/32cp7y0cf36h3xp0fqwy2nf432fpcaci-source/pkgs/servers/nosql/redis/default.nix:68",
                "unfree": false
              },
              "name": "redis-7.0.8",
              "outputs": {
                "out": "/nix/store/had7hr6vi53k6ba0p8mkhiwr2652r0rg-redis-7.0.8"
              },
              "pname": "redis",
              "system": "x86_64-darwin",
              "version": "7.0.8"
            },
            "publish_element": {
              "attrPath": [
                "evalCatalog",
                "x86_64-darwin",
                "stable",
                "redis"
              ],
              "originalUrl": "flake:nixpkgs-flox",
              "storePaths": [
                "/nix/store/had7hr6vi53k6ba0p8mkhiwr2652r0rg-redis-7.0.8"
              ],
              "url": "flake:nixpkgs-flox/34ee8469ab62af53cd25a839de33950b19126dc8"
            },
            "schema": 1,
            "source": {
              "locked": {
                "lastModified": 1676973346,
                "revCount": 456418
              }
            },
            "type": "catalogRender"
          }
        }
      }
    }
  }
}
